Workbook

Sheet Как пользоваться
A1: Tez Chakana — ручное тестирование флоу доставки: как пользоваться этим файлом
A3: Листы
A4: Тест-план | B4: Что проверяем, кто за какой ролью, соответствие экранов макета и статусов панели, порядок прогона по заказам, деньги и безопасность.
A5: Тест-кейсы | B5: Все кейсы флоу доставки. Фильтры: «Модуль», «Набор», «Приоритет», «Риск». В шагах роль указана в скобках: [Клиент], [Мерчант], [Курьер], [Оператор].
A6: Прогон | B6: Шаблон одного прогона. На каждую сборку — копия листа (ПКМ по вкладке → «Переместить или скопировать» → «Создать копию»). Названия подтягиваются из «Тест-кейсы» по ID.
A7: Баги | B7: Баги флоу доставки. Уже внесены 12 находок прогона 29.09 (заказ TEZ00871) — большинство со статусом «Перепроверить».
A8: Вопросы | B8: Вопросы к продукту и дизайну: ответ превращает вопрос в баг или в уточнение ожидаемого результата кейса.
A9: Как проходить
A10: По заказам | B10: Кейсы выполняются не по одному, а цепочкой на одном заказе — см. «Тест-план → Порядок прогона». Номер заказа пишите в «Комментарий» каждой строки прогона.
A11: Роли | B11: Вы одновременно мерчант (панель под суперадмином, отдельный браузер или профиль) и курьер (телефон). Клиент — эмулятор или телефон. Оператор — панель под ролью оператора в Chrome.
A12: Что записывать | B12: Если ожидаемый результат говорит «записать» — поведение в макете не описано: впишите факт в «Комментарий» и поставьте Pass, если поведение понятное и корректное.
A13: Время обновления | B13: На переходах засекайте, через сколько секунд статус появился у клиента (RSL-06): ≤10 с — норма, 10–30 с — замечание, >30 с — баг.
A14: Наборы (колонка «Набор»)
A15: Smoke | B15: Основной путь на одном заказе с наличными: оформление → 01 → 02 → 03 → 04 → 05 → 06 и данные у оператора и курьера. ~30 мин.
A16: Sanity | B16: Smoke + отклонение, замена, задержки, недоступный клиент, устойчивость — ключевые проверки каждого сценария.
A17: Regression | B17: Все кейсы, включая редкие ветки и мелкие проверки макета.
A18: Статусы в «Прогон»
A19: Pass | B19: Факт совпал с ожидаемым.
A20: Fail | B20: Не совпал → баг в листе «Баги», его ID — в колонку «Баг».
A21: Blocked | B21: Нельзя выполнить (неизвестен таймер, нет функции, упал предыдущий шаг) — причину в «Комментарий».
A22: Skip | B22: Сознательно пропущен.
A23: Риск (колонка)
A24: Безопасно | B24: Только просмотр.
A25: Меняет данные | B25: Меняет тестовый заказ вручную (например, ручная смена статуса оператором).
A26: Реальный заказ | B26: Создаёт настоящий заказ на боевом бэкенде. Наличные — довести до доставки или отменить; карта — обязательно проверить возврат.

Sheet Тест-план
A1: Тест-план: флоу доставки и отслеживания заказа (Customer Delivery Tracking)
A2: Составлен 2026-09-30 по макету Figma «[RFD] Client • Mobile» и прогону 29.09 на сборке 1.1.8 (43)
A4: 1. Объект и цель
A5: Что тестируем | B5: Экран отслеживания заказа в клиентском приложении (13 экранов макета: основной путь 01–06 и исключения 01A, 02A, 02B, 02C, 04A, 05A, 05B) и то, как тот же заказ видят мерчант, курьер и оператор.
A6: Цель | B6: Каждый этап и каждое исключение корректно отображаются у клиента, данные совпадают на всех сторонах, деньги считаются и возвращаются правильно.
A7: Вне области | B7: Каталог, корзина, профиль (есть в основном тест-плане TezChakana_TestPlan.xlsx), нагрузка, iOS.
A8: 2. Участники и устройства
A9: [Клиент] | B9: Клиентское приложение новой сборки, язык RU. Эмулятор Android 17 или телефон (для сети и push — телефон).
A10: [Мерчант] | B10: tez-merchant.chakana.uz под суперадмином, в отдельном браузере или профиле (иначе вытеснит сессию оператора).
A11: [Курьер] | B11: Курьерское приложение на телефоне, курьер на линии.
A12: [Оператор] | B12: tez-merchant.chakana.uz под ролью оператора (Chrome), раздел «Заказы», фильтр Pepsi Market: /orders?branch_id=79.
A13: Магазин и товары | B13: Pepsi Market, самые дешёвые позиции. Для замены (RPL) — заказ из 3 позиций.
A14: 3. Соответствие экранов макета и статусов
A15: 01 Ждём подтверждения магазина | B15: Заказ оформлен. Панель: «Подтверждён» (29.09 — сразу после оформления, статуса «Ожидает» не было). Q-D01.
A16: 02 Магазин готовит заказ | B16: Мерчант: «Готовится», затем «Готов к доставке» (клиент остаётся на 02).
A17: 02A Ищем курьера | B17: Заказ готов, курьер не принял дольше порога.
A18: 02B Некоторые товары закончились | B18: Мерчант пометил товары «нет в наличии»; у клиента таймер ответа.
A19: 02C Заказ готовится дольше | B19: Сборка идёт дольше порога.
A20: 03 Курьер забирает заказ | B20: Курьер принял заказ. Панель: ожидается «Назначен курьер» (29.09 не появился — BUG-D08).
A21: 04 Курьер в пути | B21: Курьер забрал заказ. Панель: «Передан курьеру» / «В пути».
A22: 04A Курьер задерживается | B22: Курьер не прибыл дольше порога; новое время доставки.
A23: 05 Курьер приехал | B23: Курьер «На месте», у клиента таймер ожидания. В панели такого статуса нет (Q-D02).
A24: 05A Курьер не может с вами связаться | B24: Клиент недоступен (кнопка курьера или истечение ожидания).
A25: 05B Не удалось доставить заказ | B25: Таймаут после 05A или решение. Статус панели — уточнить (Q-D14).
A26: 06 Заказ доставлен | B26: Курьер передал заказ. Панель: «Доставлен».
A27: 01A Заказ отменён | B27: Мерчант отклонил заказ. Панель: «Отменён».
A28: 4. Порядок прогона по заказам
A29: Заказ 1 — наличные | B29: Основной путь: OFR-01, OFR-02, TRK-01…TRK-05, OPR-01, OPR-02 → DLV-01, RSL-01, TRK-08, TRK-09 → DLV-02, CUR-01 → DLV-03, DLV-04, OPR-05 → RSL-04, DLV-05 → RSL-05, DLV-06, DLV-07, RSL-02, CUR-03 → DLV-08 → DLV-09, DLV-10, DLV-11, OPR-03. Попутно: TRK-06, TRK-07, OPR-04, RSL-06, CNL-04, CUR-02.
A30: Заказ 2 — наличные | B30: Отмена клиентом: CNL-01, CNL-02.
A31: Заказ 3 — карта | B31: Отклонение: OFR-03, REJ-01, REJ-03.
A32: Заказ 4 — наличные | B32: Отклонение без возврата: REJ-02.
A33: Заказ 5 — наличные, 3 позиции | B33: Замена с ответом: RPL-01, RPL-06, RPL-02, RPL-03 или RPL-04, RPL-05, RPL-10, RPL-08.
A34: Заказ 6 — карта, 3 позиции | B34: Замена без ответа: RPL-01, RPL-07 → затем REJ-05 (мерчант отменяет → полный возврат).
A35: Заказ 7 — наличные | B35: Задержки и недоступный клиент: DLY-01, DLY-02, DLY-03, DLY-04, DLY-05, DLY-07, DLY-06 → UNV-01, UNV-02, CUR-04 → UNV-03. Попутно OPR-06.
A36: Заказ 8 — карта | B36: Недоставка: до 05 → UNV-01 → UNV-04, UNV-05, CUR-05 → UNV-06, UNV-07.
A37: По желанию | B37: CNL-03 (отмена клиентом с картой), REJ-04 (автоотмена), RPL-09 (закончилось всё), OPR-07…OPR-11, RSL-03, RSL-07, RSL-08.
A38: 5. Деньги
A39: Наличные | B39: Заказы 1, 2, 4, 5, 7 — деньги не списываются; доводим до доставки или отмены.
A40: Карта | B40: Заказы 3, 6, 8 — только там, где ожидается возврат. Каждый такой заказ довести до возврата и проверить поступление в банке; сумму и статус записать в «Комментарий».
A41: 6. Безопасность
A42: Боевой бэкенд | B42: Работаем только со своими тестовыми заказами. Чужие заказы в панели не открывать и не менять, их данные никуда не переносить.
A43: Панель | B43: Ручную смену статуса (OPR-08) — только на своём тестовом заказе. По ссылке Telegram поддержки в панели не переходить (BUG-D09).
A44: Не оставлять хвостов | B44: Прерванный сценарий — отменить заказ как мерчант; для карты проверить возврат.
A45: 7. Критерии
A46: Флоу годен | B46: Все P0 — Pass; нет открытых Critical; суммы у клиента, в панели и у курьера совпадают; возвраты по карте приходят.
A47: Флоу не годен | B47: Любой Fail в Smoke; статус не доходит до клиента; неверные суммы или возвраты; заказ «застревает» на этапе.
A48: Приоритет кейса | B48: P0 — без этого заказ не доставить или теряются деньги. P1 — важная ветка флоу. P2 — редкий случай, внешний вид.
A49: Серьёзность бага | B49: Critical — деньги, безопасность, флоу не проходит. Major — неверные данные или этап, есть обход. Minor — текст, формат, мелкая логика. Trivial — внешний вид.

Sheet Тест-кейсы
A1: ID | B1: Модуль | C1: Название | D1: Предусловия | E1: Шаги | F1: Ожидаемый результат | G1: Приоритет | H1: Тип | I1: Набор | J1: Риск | K1: Автотест | L1: Примечание / баг | N1: Сводка | O1: Кол-во
A2: OFR-01 | B2: Оформление | C2: Оформление заказа с доставкой, наличные | D2: Клиент авторизован, язык RU, сборка с новым флоу доставки; активных заказов нет; адрес в зоне Pepsi Market; мерчант открыт в отдельном браузере; курьер на линии; оператор: /orders?branch_id=79 | E2: 1. [Клиент] Pepsi Market → добавить 1 самую дешёвую позицию → Корзина → оформление. 2. Проверить блок стоимости: товары, доставка, итог. 3. Выбрать «Наличные», оформить заказ. 4. [Клиент] Открыть «Заказы». | F2: На экране оформления видна стоимость доставки; Итог = товары + доставка. После оформления — экран успеха, затем отслеживание (экран 01). В «Заказах» ровно один новый заказ, дублей нет. | G2: P0 | H2: + | I2: Smoke | J2: Реальный заказ | L2: 29.09 (TEZ00871): доставка на оформлении не показана; Итог 2 000 без доставки 12 000 — BUG-D01, BUG-D02 | N2: Всего кейсов | O2: =COUNTA(A2:A81) -> 80
A3: OFR-02 | B3: Оформление | C3: Экран успеха после оформления | D3: Выполнен шаг 3 из OFR-01 | E3: 1. [Клиент] Рассмотреть экран успеха до перехода на отслеживание. 2. Сверить с экраном оформления и с часами устройства. | F3: Стоимость доставки = сумме на оформлении и в панели; подпись «Способ оплаты»; время в 24-часовом формате и совпадает с часами устройства; переход к заказу работает. | G3: P1 | H3: + | I3: Sanity | J3: Реальный заказ | L3: 29.09: «Стоимость доставки 0 сум», «Способ пополнения», 04:34 вместо 16:34 — BUG-D03, BUG-D04, BUG-D05 | N3: Smoke | O3: =COUNTIF(I2:I81,"Smoke") -> 11
A4: OFR-03 | B4: Оформление | C4: Оформление заказа картой | D4: Клиент авторизован, язык RU, сборка с новым флоу доставки; активных заказов нет; адрес в зоне Pepsi Market; мерчант открыт в отдельном браузере; курьер на линии; оператор: /orders?branch_id=79; есть сохранённая карта | E4: 1. [Клиент] Pepsi Market → 1 дешёвая позиция → оформление. 2. Выбрать сохранённую карту, оформить. 3. [Оператор] Открыть карточку заказа. | F4: Клиент: экран 01, «Способ оплаты — Через карту ** XXXX» с верными цифрами. Оператор: «Оплата: Карта», «Оплачено: Да», сумма = Итог клиента. Списание в банке = Итог. | G4: P1 | H4: + | I4: Sanity | J4: Реальный заказ | L4: После проверки довести заказ до возврата (REJ-01 или CNL-03). Карты не добавлять и не удалять | N4: Sanity (вкл. Smoke) | O4: =COUNTIF(I2:I81,"Smoke")+COUNTIF(I2:I81,"Sanity") -> 58
A5: TRK-01 | B5: Отслеживание | C5: Экран 01 «Ждём подтверждения магазина» | D5: Заказ только что оформлен (OFR-01) | E5: 1. [Клиент] Открыть экран отслеживания. 2. Сверить все элементы с макетом. | F5: Заголовок «Ждём подтверждения магазина»; подзаголовок «Обычно это занимает 1-3 минуты»; степпер: шаг 1 (часы) активен, остальные серые; текст «Сообщим, когда магазин начнет сборку»; карточки «Адрес доставки» (верный адрес), «Ваш заказ — Товаров N шт — Посмотреть», «Способ оплаты», «Общая стоимость» с подсказкой «Итог может измениться при замене или изменении веса товаров»; сверху шеврон и «Помощь». | G5: P0 | H5: + | I5: Smoke | J5: Реальный заказ | L5: На 01 в сборке есть иконка отмены — см. CNL-01 | N5: Regression (все) | O5: =COUNTA(A2:A81) -> 80
A6: TRK-02 | B6: Отслеживание | C6: «Посмотреть» — состав заказа | D6: Заказ Pepsi Market (наличные); клиент на экране любом | E6: 1. [Клиент] В карточке «Ваш заказ» нажать «Посмотреть». 2. Вернуться назад. | F6: Открывается состав: товары, количество, цены, как при оформлении. Назад — тот же экран отслеживания с текущим статусом. | G6: P1 | H6: + | I6: Sanity | J6: Реальный заказ | N6: P0 | O6: =COUNTIF(G2:G81,"P0") -> 15
A7: TRK-03 | B7: Отслеживание | C7: Кнопка «Помощь» | D7: Заказ Pepsi Market (наличные); клиент на экране любом | E7: 1. [Клиент] Нажать «Помощь». 2. Проверить, куда ведёт каждый контакт (без реального звонка/сообщения). 3. Вернуться. | F7: Открывается поддержка; телефон и Telegram — официальные контакты сервиса. Возврат на отслеживание без потери состояния. | G7: P1 | H7: + | I7: Sanity | J7: Реальный заказ | L7: В панели ссылка Telegram поддержки ведёт на oastify.com — проверить и в приложении (BUG-D09) | N7: P1 | O7: =COUNTIF(G2:G81,"P1") -> 46
A8: TRK-04 | B8: Отслеживание | C8: Шеврон «свернуть» и возврат к заказу | D8: Заказ Pepsi Market (наличные); клиент на экране любом | E8: 1. [Клиент] Нажать шеврон. 2. Найти активный заказ (Home / «Заказы»), открыть. | F8: Экран сворачивается, активный заказ доступен с Home или из «Заказов»; при открытии — текущий статус. | G8: P2 | H8: + | I8: Regression | J8: Реальный заказ | N8: P2 | O8: =COUNTIF(G2:G81,"P2") -> 19
A9: TRK-05 | B9: Отслеживание | C9: Блок «Общая стоимость» | D9: Заказ Pepsi Market (наличные); клиент на экране 01 | E9: 1. [Клиент] Проверить строки «За товары», «Доставка», «Итог». 2. [Оператор] Сравнить с блоком «Товары / Доставка / Итого» в карточке. | F9: За товары = сумма позиций; Доставка = сумма или «Бесплатно»; Итог = За товары + Доставка; значения совпадают с панелью. | G9: P0 | H9: + | I9: Smoke | J9: Реальный заказ | L9: 29.09: Итог 2 000, доставка 12 000 в итог не вошла (клиент и панель) — BUG-D01 | N9: Негативные (−) | O9: =COUNTIF(H2:H81,"−") -> 5
A10: TRK-06 | B10: Отслеживание | C10: Подсказка «Итог может измениться…» по этапам | D10: Выполняется попутно с DLV-, RPL-, DLY-, UNV-кейсами | E10: 1. [Клиент] На каждом экране отметить, есть ли подсказка под итогом. | F10: Есть на 01, 02, 02A, 02B, 02C, 03; нет на 04, 04A, 05, 05A, 05B, 06, 01A. | G10: P2 | H10: + | I10: Regression | J10: Реальный заказ | L10: Q-D08: зачем подсказка на 03 и 02A, если заказ уже собран | N10: Реальный заказ | O10: =COUNTIF(J2:J81,"Реальный заказ") -> 69
A11: TRK-07 | B11: Отслеживание | C11: Степпер соответствует этапу | D11: Выполняется попутно со всеми сценариями | E11: 1. [Клиент] На каждом экране проверить, какой шаг степпера активен и какие пройдены. | F11: 01 — шаг 1; 02/02A/02B/02C/03 — шаг 2; 04/04A/05/05A — шаг 3; 06 — все шаги зелёные. Активный — красный круг с белой иконкой, пройденные — светло-красные, будущие — серые. На 01A степпера нет. | G11: P1 | H11: + | I11: Sanity | J11: Реальный заказ | L11: Проверяется только визуально
A12: TRK-08 | B12: Отслеживание | C12: Открытие активного заказа из «Заказов» | D12: Заказ Pepsi Market (наличные); клиент на экране 02 | E12: 1. [Клиент] Закрыть отслеживание. 2. «Заказы» → активный заказ. | F12: Открывается тот же экран отслеживания с текущим статусом, ETA и данными. | G12: P1 | H12: + | I12: Sanity | J12: Реальный заказ
A13: TRK-09 | B13: Отслеживание | C13: Формат времени доставки | D13: Заказ Pepsi Market (наличные); клиент на экране 02 | E13: 1. [Клиент] Проверить строку «Ожидаемая доставка». | F13: Формат «HH:MM-HH:MM», 24 часа, время в будущем относительно текущего, интервал выделен жирным. | G13: P2 | H13: + | I13: Regression | J13: Реальный заказ
A14: DLV-01 | B14: Основной путь | C14: Мерчант взял заказ в работу → экран 02 | D14: Заказ Pepsi Market (наличные); клиент на экране 01 | E14: 1. [Мерчант] Перевести заказ в «Готовится». 2. [Клиент] Не трогая эмулятор, смотреть на экран. 3. [Оператор] Обновить карточку заказа. | F14: Клиент за ≤10 с: «Магазин готовит заказ», «Ожидаемая доставка HH:MM-HH:MM», шаг 2 активен, «Собираем ваши товары», иконка отмены исчезла. Оператор: статус «Готовится», в истории «Мерчант: Готовится», время, автор. | G14: P0 | H14: + | I14: Smoke | J14: Реальный заказ | L14: 29.09: работает (клиент перешёл на 02 после «Готовится» мерчанта)
A15: DLV-02 | B15: Основной путь | C15: «Готов к доставке» — клиент остаётся на 02 | D15: Заказ Pepsi Market (наличные); клиент на экране 02 | E15: 1. [Мерчант] Перевести заказ в «Готов к доставке». 2. [Клиент] Смотреть на экран 30 с. 3. [Курьер] Открыть ленту заказов. | F15: Клиент остаётся на 02, ETA не меняется. Оператор: «Готов к доставке». Курьер: заказ в ленте — магазин, адрес клиента, сумма к получению = Итог клиента. | G15: P1 | H15: + | I15: Sanity | J15: Реальный заказ | L15: По макету READY отдельного экрана не имеет
A16: DLV-03 | B16: Основной путь | C16: Курьер принял заказ → экран 03 | D16: Заказ Pepsi Market (наличные); клиент на экране 02; заказ «Готов к доставке» | E16: 1. [Курьер] Принять заказ. 2. [Клиент] Смотреть на экран. 3. [Оператор] Обновить карточку и список. | F16: Клиент: «Курьер забирает заказ», ETA, шаг 2 активен, «Курьер направляется за вашим заказом», карточка «Ваш курьер» с именем курьера и кнопкой «Позвонить». Оператор: «Назначен курьер», курьер виден в списке и в карточке. | G16: P0 | H16: + | I16: Smoke | J16: Реальный заказ | L16: 29.09: в панели сразу «В пути», без «Назначен курьер»; курьер только в списке — BUG-D08 (перепроверить)
A17: DLV-04 | B17: Основной путь | C17: «Позвонить» в карточке курьера | D17: Заказ Pepsi Market (наличные); клиент на экране 03 | E17: 1. [Клиент] Нажать «Позвонить». 2. Сверить номер, не звонить, вернуться. | F17: Открывается набор номера с телефоном курьера (номер курьерского аккаунта). Возврат на отслеживание. | G17: P1 | H17: + | I17: Sanity | J17: Реальный заказ
A18: DLV-05 | B18: Основной путь | C18: Курьер забрал заказ → экран 04 | D18: Заказ Pepsi Market (наличные); клиент на экране 03 | E18: 1. [Курьер] Отметить, что забрал заказ в магазине. 2. [Клиент] Смотреть на экран. 3. [Оператор] Обновить. | F18: Клиент: «Курьер в пути», ETA, «Ваш заказ уже едет к вам», шаг 3 активен, карточка курьера, подсказки итога нет. Оператор: «Передан курьеру» / «В пути». | G18: P0 | H18: + | I18: Smoke | J18: Реальный заказ
A19: DLV-06 | B19: Основной путь | C19: Курьер на месте → экран 05 | D19: Заказ Pepsi Market (наличные); клиент на экране 04 | E19: 1. [Курьер] Нажать «На месте». 2. [Клиент] Смотреть на экран. 3. [Оператор] Обновить. | F19: Клиент: «Курьер приехал», «Ожидает MM:SS» с обратным отсчётом, «Курьер ждёт вас у места доставки», шаг 3. Таймер у курьера ≈ таймеру клиента (±5 с). Оператор: прибытие видно (статус или запись в истории). | G19: P0 | H19: + | I19: Smoke | J19: Реальный заказ | L19: Q-D02: в панели нет статуса «Курьер на месте»
A20: DLV-07 | B20: Основной путь | C20: Таймер ожидания на экране 05 | D20: Заказ Pepsi Market (наличные); клиент на экране 05 | E20: 1. [Клиент] Наблюдать таймер 1 мин. 2. Закрыть и открыть экран. 3. (Опц.) Дождаться 00:00, курьер ничего не жмёт. | F20: Отсчёт идёт каждую секунду, после переоткрытия не сбрасывается. На 00:00 — поведение по правилам сервиса (записать: переход на 05A или остаётся 05). | G20: P1 | H20: + | I20: Sanity | J20: Реальный заказ
A21: DLV-08 | B21: Основной путь | C21: Курьер передал заказ → экран 06 | D21: Заказ Pepsi Market (наличные); клиент на экране 05 | E21: 1. [Курьер] Отметить передачу (получил наличные). 2. [Клиент] Смотреть на экран. 3. [Оператор] Обновить. | F21: Клиент: «Заказ доставлен, HH:MM» (фактическое время), «Спасибо за заказ!», все шаги зелёные, блок «Как прошла доставка?», 5 звёзд, «Сообщить о проблеме»; карточки только «Ваш заказ» и «Общая стоимость». Оператор: «Доставлен», время совпадает, «Оплачено: Да». Курьер: заказ закрыт. | G21: P0 | H21: + | I21: Smoke | J21: Реальный заказ
A22: DLV-09 | B22: Основной путь | C22: Оценка доставки | D22: Заказ Pepsi Market (наличные); клиент на экране 06 | E22: 1. [Клиент] Поставить 5 звёзд. 2. Закрыть и открыть заказ. 3. (Отдельный заказ) Поставить 1–2 звезды. | F22: Оценка принимается, повторно не запрашивается. При низкой оценке — форма комментария или причины (записать). Оператор видит оценку, если панель это показывает. | G22: P1 | H22: + | I22: Sanity | J22: Реальный заказ
A23: DLV-10 | B23: Основной путь | C23: «Сообщить о проблеме» на экране 06 | D23: Заказ Pepsi Market (наличные); клиент на экране 06 | E23: 1. [Клиент] Нажать «Сообщить о проблеме». 2. Закрыть без отправки. | F23: Открывается форма или поддержка; закрытие возвращает на 06 без изменений. | G23: P2 | H23: + | I23: Regression | J23: Реальный заказ
A24: DLV-11 | B24: Основной путь | C24: Доставленный заказ уходит из активных | D24: Заказ Pepsi Market (наличные); клиент на экране 06 | E24: 1. [Клиент] Перезапустить приложение. 2. Открыть «Заказы». | F24: Активного отслеживания нет; заказ в истории со статусом «Доставлен» и верной суммой. | G24: P1 | H24: + | I24: Sanity | J24: Реальный заказ
A25: CNL-01 | B25: Отмена клиентом | C25: Иконка отмены на 01 — отказ от отмены | D25: Заказ Pepsi Market (наличные); клиент на экране 01 | E25: 1. [Клиент] Нажать иконку отмены (корзина). 2. Ввести причину. 3. Нажать «Нет» / закрыть диалог. | F25: Диалог отмены с полем причины. После «Нет» заказ не тронут: экран 01, в панели статус не изменился. | G25: P1 | H25: ± | I25: Sanity | J25: Реальный заказ | L25: В макете отмены клиентом нет, в сборке есть — Q-D03
A26: CNL-02 | B26: Отмена клиентом | C26: Отмена заказа клиентом на 01, наличные | D26: Заказ Pepsi Market (наличные); клиент на экране 01 | E26: 1. [Клиент] Иконка отмены → причина → подтвердить. 2. [Оператор] Обновить карточку. 3. [Мерчант] Открыть заказ. | F26: Клиент: экран отменённого заказа (записать текст), заказ не в активных. Оператор: «Отменён», автор — клиент, причина сохранена. Мерчант: заказ отменён, в работу не взять. Курьеру заказ не предлагается. | G26: P1 | H26: + | I26: Sanity | J26: Реальный заказ
A27: CNL-03 | B27: Отмена клиентом | C27: Отмена клиентом, оплата картой — возврат | D27: Заказ Pepsi Market (карта); клиент на экране 01 | E27: 1. [Клиент] Отменить заказ на 01. 2. [Оператор] Проверить оплату/возврат. 3. Проверить поступление в банке (позже). | F27: Клиент видит информацию о возврате (сумма = Итог, маска карты). Оператор: «Отменён», статус возврата. Деньги вернулись на карту. | G27: P1 | H27: + | I27: Regression | J27: Реальный заказ
A28: CNL-04 | B28: Отмена клиентом | C28: После начала сборки отмены нет | D28: Заказ Pepsi Market (наличные); клиент на экране 02 | E28: 1. [Клиент] Проверить экраны 02, 03, 04, 05 на наличие иконки отмены. | F28: Иконки отмены нет начиная с 02. | G28: P1 | H28: − | I28: Sanity | J28: Реальный заказ | L28: 29.09: на 02 иконка исчезла — ок
A29: REJ-01 | B29: Отклонение | C29: Мерчант отклонил заказ, оплата картой → 01A | D29: Заказ Pepsi Market (карта); клиент на экране 01 | E29: 1. [Мерчант] Отклонить заказ (с причиной). 2. [Клиент] Смотреть на экран. 3. [Оператор] Обновить. 4. [Курьер] Проверить ленту. | F29: Клиент: «Заказ отменён», «Магазин не смог принять заказ», красный блок «Возврат оплаты: <Итог> сум вернём на карту ** XXXX. Срок возврата зависит от банка.»; степпера и подсказки итога нет. Оператор: «Отменён», причина, автор мерчант, статус возврата. Курьеру заказ не приходил. | G29: P0 | H29: + | I29: Sanity | J29: Реальный заказ | L29: Проверить поступление возврата в банке
A30: REJ-02 | B30: Отклонение | C30: Мерчант отклонил заказ, наличные | D30: Заказ Pepsi Market (наличные); клиент на экране 01 | E30: 1. [Мерчант] Отклонить заказ. 2. [Клиент] Смотреть на экран. | F30: 01A без блока возврата (записать, что показано вместо него). Оператор: «Отменён», возврата нет. | G30: P1 | H30: + | I30: Sanity | J30: Реальный заказ | L30: Q-D06: в макете вариант для наличных не описан
A31: REJ-03 | B31: Отклонение | C31: Отменённый заказ не возвращается в активный флоу | D31: Выполнен REJ-01 или REJ-02 | E31: 1. [Клиент] Перезапустить приложение. 2. Открыть Home и «Заказы». | F31: Активного заказа нет; в истории статус «Отменён». | G31: P1 | H31: + | I31: Sanity | J31: Реальный заказ
A32: REJ-04 | B32: Отклонение | C32: Автоотмена без подтверждения магазина | D32: Заказ Pepsi Market (наличные); клиент на экране 01; известен таймаут подтверждения | E32: 1. [Мерчант] Ничего не делать до конца таймаута. 2. [Клиент] Смотреть на экран. | F32: Клиент: 01A. Оператор: «Отменён», причина — таймаут. | G32: P2 | H32: − | I32: Regression | J32: Реальный заказ | L32: Выполнять, только если автоотмена существует (Q-D05)
A33: REJ-05 | B33: Отклонение | C33: Мерчант отменил заказ после начала сборки | D33: Заказ Pepsi Market (карта); клиент на экране 02 | E33: 1. [Мерчант] Отменить заказ в статусе «Готовится». 2. [Клиент] Смотреть на экран. 3. [Оператор] Проверить возврат. | F33: Клиент: понятный экран отмены с информацией о возврате (записать, какой). Оператор: «Отменён», возврат полной списанной суммы. | G33: P2 | H33: + | I33: Regression | J33: Реальный заказ | L33: В макете не описано — Q-D07
A34: RPL-01 | B34: Замена | C34: Товары закончились → экран 02B | D34: Заказ Pepsi Market из 3 позиций (A, B, C), наличные; статус «Готовится»; клиент на 02 | E34: 1. [Мерчант] Пометить A и B «нет в наличии», для A предложить замену (лучше с другой ценой). 2. [Клиент] Смотреть на экран. 3. [Оператор] Обновить. | F34: Клиент: «Некоторые товары закончились», «2 товара закончились. Ответьте, чтобы магазин продолжил сборку.», жёлтый блок «Осталось MM:SS. Если не ответите, недоступные товары будут удалены из заказа.», таймер идёт, «Решено 0 из 2»; A — «Нет в наличии» → «Предлагаем замену» (название, вес, цена), кнопки «Удалить» / «Заменить»; B — «Нужна замена», «Выбрать». Оператор: признак ожидания замены (записать, как показан). | G34: P0 | H34: + | I34: Sanity | J34: Реальный заказ
A35: RPL-02 | B35: Замена | C35: Принять предложенную замену | D35: Заказ Pepsi Market (наличные); клиент на экране 02B | E35: 1. [Клиент] У товара A нажать «Заменить». 2. [Мерчант] Открыть заказ. | F35: «Решено 1 из 2», A отмечен как решённый. Мерчант видит выбор клиента. | G35: P0 | H35: + | I35: Sanity | J35: Реальный заказ
A36: RPL-03 | B36: Замена | C36: Удалить недоступный товар | D36: Заказ Pepsi Market (наличные); клиент на экране 02B | E36: 1. [Клиент] У товара нажать «Удалить». | F36: Счётчик «Решено» увеличился; товар помечен как удалённый. | G36: P1 | H36: + | I36: Regression | J36: Реальный заказ
A37: RPL-04 | B37: Замена | C37: «Выбрать» замену самому | D37: Заказ Pepsi Market (наличные); клиент на экране 02B | E37: 1. [Клиент] У товара B нажать «Выбрать». 2. Выбрать замену, подтвердить. | F37: Открывается экран выбора замены (записать какой); после выбора B решён, счётчик увеличился. | G37: P1 | H37: + | I37: Regression | J37: Реальный заказ | L37: Q-D12: экран выбора в макете не показан
A38: RPL-05 | B38: Замена | C38: Все товары решены → возврат на 02, пересчёт | D38: Заказ Pepsi Market (наличные); клиент на экране 02B; решён 1 из 2 | E38: 1. [Клиент] Решить последний товар. 2. Проверить экран, «Товаров N шт» и блок стоимости. 3. [Оператор] Обновить карточку. | F38: «Решено 2 из 2» → экран 02. Количество и Итог пересчитаны (разница цены замены, удалённые товары). Состав и Итого в панели совпадают с клиентом. Мерчант продолжает сборку. | G38: P0 | H38: + | I38: Sanity | J38: Реальный заказ
A39: RPL-06 | B39: Замена | C39: Таймер замены после перезапуска | D39: Заказ Pepsi Market (наличные); клиент на экране 02B | E39: 1. [Клиент] Запомнить таймер, убить приложение. 2. Через 20 с открыть. | F39: Снова 02B; таймер продолжился (меньше на ~20 с), не сброшен; «Решено X из N» сохранилось. | G39: P1 | H39: + | I39: Sanity | J39: Реальный заказ
A40: RPL-07 | B40: Замена | C40: Клиент не ответил — автоудаление | D40: Заказ из 3 позиций, оплата картой; мерчант пометил 2 товара «нет в наличии»; клиент на 02B | E40: 1. [Клиент] Ничего не делать до конца таймера. 2. Проверить экран и суммы. 3. [Оператор] Проверить состав, историю, оплату. | F40: На 00:00 товары удалены, возврат на 02, количество и Итог уменьшены; таймер не уходит в минус. Оператор: товары удалены автоматически (запись в истории), сумма пересчитана, возврат/корректировка по карте. | G40: P1 | H40: + | I40: Sanity | J40: Реальный заказ | L40: Q-D09: как клиенту показывается удаление
A41: RPL-08 | B41: Замена | C41: Итог после замены на всех сторонах | D41: Выполнен RPL-05 (наличные) | E41: 1. [Мерчант] «Готов к доставке». 2. [Курьер] Принять → забрал → на месте → передал. 3. Сверить суммы. | F41: Итог на 06 = пересчитанному; сумма к получению у курьера = новому Итогу; «Итого» в панели = тому же. | G41: P1 | H41: + | I41: Sanity | J41: Реальный заказ
A42: RPL-09 | B42: Замена | C42: Закончились все товары заказа | D42: Заказ из 1–2 позиций; статус «Готовится» | E42: 1. [Мерчант] Пометить все товары «нет в наличии» без замены. 2. [Клиент] Удалить все. | F42: Понятное поведение: заказ отменяется с информацией для клиента (записать). Нет пустого заказа в доставке. | G42: P2 | H42: − | I42: Regression | J42: Реальный заказ | L42: Не описано в макете — Q-D09
A43: RPL-10 | B43: Замена | C43: Замена с другой ценой | D43: Заказ Pepsi Market (наличные); клиент на экране 02B | E43: 1. [Мерчант] Предложить замену дороже (или дешевле) оригинала. 2. [Клиент] Принять. | F43: Итог изменился на разницу; для карты — доплата или возврат разницы отражены у оператора. | G43: P2 | H43: + | I43: Regression | J43: Реальный заказ
A44: DLY-01 | B44: Задержки | C44: Сборка дольше обычного → экран 02C | D44: Заказ Pepsi Market (наличные); клиент на экране 02; известен порог задержки сборки | E44: 1. [Мерчант] Не завершать сборку дольше порога. 2. [Клиент] Смотреть на экран. 3. [Оператор] Обновить. | F44: Клиент: «Заказ готовится дольше», «Уточняем новое время доставки», «Магазину нужно немного больше времени», жёлтый блок «Сборка занимает больше времени…», шаг 2. Оператор: заказ заметен как задержанный (записать, как). | G44: P1 | H44: + | I44: Sanity | J44: Реальный заказ | L44: Если порог неизвестен — записать фактическое время появления
A45: DLY-02 | B45: Задержки | C45: Сборка завершена после задержки → 02 с новым ETA | D45: Заказ Pepsi Market (наличные); клиент на экране 02C | E45: 1. [Мерчант] «Готов к доставке». 2. [Клиент] Смотреть на экран. | F45: Экран 02 с новым ETA (позже первоначального); баннер задержки пропал. | G45: P1 | H45: + | I45: Sanity | J45: Реальный заказ
A46: DLY-03 | B46: Задержки | C46: Долгий поиск курьера → экран 02A | D46: Заказ Pepsi Market (наличные); клиент на экране 02; заказ «Готов к доставке» | E46: 1. [Курьер] Не принимать заказ дольше порога. 2. [Клиент] Смотреть на экран. | F46: Клиент: «Ищем курьера», «Уточняем новое время доставки», жёлтый блок «Поиск занимает больше времени. Заказ уже собран. Сообщим, как только найдём курьера.» Оператор: признак задержки (записать). | G46: P1 | H46: + | I46: Sanity | J46: Реальный заказ | L46: Q-D10: «заказ уже собран», а степпер на сборке
A47: DLY-04 | B47: Задержки | C47: Курьер найден после задержки → экран 03 | D47: Заказ Pepsi Market (наличные); клиент на экране 02A | E47: 1. [Курьер] Принять заказ. | F47: Клиент: экран 03 с ETA и карточкой курьера; баннер пропал. | G47: P1 | H47: + | I47: Sanity | J47: Реальный заказ
A48: DLY-05 | B48: Задержки | C48: Курьер задерживается в пути → экран 04A | D48: Заказ Pepsi Market (наличные); клиент на экране 04; известен порог задержки доставки | E48: 1. [Курьер] Не нажимать «На месте» дольше порога. 2. [Клиент] Смотреть на экран. | F48: Клиент: «Курьер задерживается», «Новое время доставки HH:MM-HH:MM», «Курьер уже едет к вам», жёлтый блок «Доставка займёт немного больше времени…», карточка курьера, шаг 3. Новое время позже прежнего. | G48: P1 | H48: + | I48: Sanity | J48: Реальный заказ | L48: Макет: время на 04A не жирное (Q-D13)
A49: DLY-06 | B49: Задержки | C49: Прибытие после задержки → экран 05 | D49: Заказ Pepsi Market (наличные); клиент на экране 04A | E49: 1. [Курьер] «На месте». | F49: Экран 05, баннер задержки пропал, таймер ожидания запущен. | G49: P1 | H49: + | I49: Sanity | J49: Реальный заказ
A50: DLY-07 | B50: Задержки | C50: Новое время одинаково у клиента и курьера | D50: Заказ Pepsi Market (наличные); клиент на экране 04A | E50: 1. Сравнить новое время доставки у клиента и в курьерском приложении. | F50: Время совпадает (если курьерское приложение показывает ETA). | G50: P2 | H50: + | I50: Regression | J50: Реальный заказ
A51: UNV-01 | B51: Недоступен | C51: Клиент недоступен → экран 05A | D51: Заказ Pepsi Market (наличные); клиент на экране 05 | E51: 1. [Курьер] «Клиент не отвечает» (или дождаться конца таймера ожидания — как устроено). 2. [Клиент] Смотреть. 3. [Оператор] Обновить. | F51: Клиент: «Курьер не может с вами связаться», «Курьер ждёт у места доставки», жёлтый блок «Свяжитесь с курьером…», красная кнопка «Позвонить курьеру», карточка курьера, шаг 3. Оператор: проблема заметна (записать, как). | G51: P1 | H51: + | I51: Sanity | J51: Реальный заказ | L51: Q-D11: нужен ли на 05A таймер ожидания
A52: UNV-02 | B52: Недоступен | C52: «Позвонить курьеру» на 05A | D52: Заказ Pepsi Market (наличные); клиент на экране 05A | E52: 1. [Клиент] Нажать «Позвонить курьеру». 2. Сверить номер, не звонить, вернуться. | F52: Набор номера с телефоном курьера. | G52: P1 | H52: + | I52: Sanity | J52: Реальный заказ
A53: UNV-03 | B53: Недоступен | C53: Передача после 05A → экран 06 | D53: Заказ Pepsi Market (наличные); клиент на экране 05A | E53: 1. [Курьер] Передал заказ. | F53: Клиент: 06. Оператор: «Доставлен», признак проблемы снят. | G53: P1 | H53: + | I53: Sanity | J53: Реальный заказ
A54: UNV-04 | B54: Недоступен | C54: Таймаут → экран 05B «Не удалось доставить» | D54: Заказ Pepsi Market (карта); клиент на экране 05A | E54: 1. Никто ничего не делает до таймаута (или мерчант переводит в «не доставлен» — как устроено). 2. [Клиент] Смотреть. 3. [Оператор] Обновить. 4. [Курьер] Проверить приложение. | F54: Клиент: «Не удалось доставить заказ», «Курьер не смог передать вам заказ», красный блок «Доставка не состоялась. Мы проверим ситуацию и сообщим, что произойдёт с заказом и оплатой.», кнопка «Связаться с поддержкой», карточки курьера нет. Оператор: финальный статус (записать — «Возвращён»?). Курьер: инструкция, что делать с заказом. | G54: P1 | H54: + | I54: Sanity | J54: Реальный заказ | L54: Q-D14: какой статус в панели соответствует недоставке
A55: UNV-05 | B55: Недоступен | C55: «Связаться с поддержкой» на 05B | D55: Заказ Pepsi Market (карта); клиент на экране 05B | E55: 1. [Клиент] Нажать «Связаться с поддержкой». 2. Вернуться. | F55: Открывается канал поддержки (официальный контакт). | G55: P2 | H55: + | I55: Regression | J55: Реальный заказ
A56: UNV-06 | B56: Недоступен | C56: Возврат после недоставки (карта) | D56: Заказ Pepsi Market (карта); клиент на экране 05B | E56: 1. [Мерчант] Принять решение по заказу — возврат. 2. [Клиент] Проверить экран. 3. [Оператор] Проверить возврат. | F56: Клиент видит итог решения и информацию о возврате (записать). Оператор: статус возврата, сумма = списанной. | G56: P1 | H56: + | I56: Sanity | J56: Реальный заказ | L56: В макете не описано — Q-D07
A57: UNV-07 | B57: Недоступен | C57: Недоставленный заказ не возвращается в активный флоу | D57: Выполнен UNV-04 | E57: 1. [Клиент] Перезапустить приложение. 2. Открыть «Заказы». | F57: Активного заказа нет; статус в истории понятен клиенту. | G57: P2 | H57: + | I57: Regression | J57: Реальный заказ
A58: RSL-01 | B58: Устойчивость | C58: Перезапуск приложения на 02 | D58: Заказ Pepsi Market (наличные); клиент на экране 02 | E58: 1. [Клиент] Смахнуть приложение из недавних. 2. Открыть заново, открыть заказ. | F58: Сразу экран 02 с тем же ETA, без мелькания 01. Вход сохранён. | G58: P1 | H58: + | I58: Sanity | J58: Реальный заказ | L58: На эмуляторе после запуска появляется диалог уведомлений — закрыть
A59: RSL-02 | B59: Устойчивость | C59: Перезапуск на 05 — таймер ожидания | D59: Заказ Pepsi Market (наличные); клиент на экране 05 | E59: 1. [Клиент] Запомнить таймер, убить приложение. 2. Через 20 с открыть. | F59: Экран 05, таймер меньше на ~20 с, не сброшен. | G59: P1 | H59: + | I59: Sanity | J59: Реальный заказ
A60: RSL-03 | B60: Устойчивость | C60: Сворачивание на 30 с | D60: Заказ Pepsi Market (наличные); клиент на экране любом | E60: 1. [Клиент] Свернуть приложение на 30 с. 2. Вернуться. | F60: Тот же экран, актуальный статус, таймеры продолжили отсчёт. | G60: P2 | H60: + | I60: Regression | J60: Реальный заказ
A61: RSL-04 | B61: Устойчивость | C61: Смена статуса, пока приложение свёрнуто | D61: Заказ Pepsi Market (наличные); клиент на экране 03 | E61: 1. [Клиент] Свернуть приложение. 2. [Курьер] Отметить «Забрал». 3. [Клиент] Вернуться в приложение. | F61: Сразу экран 04, без перезапуска. | G61: P1 | H61: + | I61: Sanity | J61: Реальный заказ
A62: RSL-05 | B62: Устойчивость | C62: Нет сети во время смены статуса | D62: Заказ Pepsi Market (наличные); клиент на экране 04 | E62: 1. [Клиент] Выключить Wi-Fi и мобильные данные. 2. [Курьер] «На месте». 3. [Клиент] Через 30 с включить сеть. | F62: Без сети — экран не падает (есть индикатор офлайна или прежний статус). После включения — экран 05 без перезапуска. | G62: P1 | H62: ± | I62: Sanity | J62: Реальный заказ | L62: Выполнять на телефоне: на эмуляторе отключение сети не рвёт открытые соединения — результат недостоверен
A63: RSL-06 | B63: Устойчивость | C63: Скорость обновления статуса | D63: Выполняется попутно с DLV-01…DLV-08 | E63: 1. На каждом переходе засечь время от действия мерчанта/курьера до смены экрана у клиента и статуса у оператора. | F63: Клиент ≤10 с; оператор — после обновления страницы статус уже новый. | G63: P1 | H63: + | I63: Sanity | J63: Реальный заказ | L63: 10–30 с — замечание, >30 с — баг
A64: RSL-07 | B64: Устойчивость | C64: Push-уведомления о смене статуса | D64: Клиент авторизован, язык RU, сборка с новым флоу доставки; активных заказов нет; адрес в зоне Pepsi Market; мерчант открыт в отдельном браузере; курьер на линии; оператор: /orders?branch_id=79; уведомления разрешены; приложение свёрнуто | E64: 1. Пройти основной путь и сценарии отклонения/недоставки. 2. Отмечать уведомления. 3. Нажать на одно из них. | F64: Уведомления на ключевых переходах (02, 03, 05, 05A, 06, 01A, 05B) с понятным текстом; тап открывает отслеживание этого заказа. | G64: P1 | H64: + | I64: Sanity | J64: Реальный заказ | L64: Лучше на реальном телефоне
A65: RSL-08 | B65: Устойчивость | C65: Открытие из уведомления при закрытом приложении | D65: Приложение смахнуто; пришло уведомление о смене статуса | E65: 1. Нажать на уведомление. | F65: Приложение запускается и открывает отслеживание этого заказа с текущим статусом. | G65: P2 | H65: + | I65: Regression | J65: Реальный заказ
A66: OPR-01 | B66: Оператор | C66: Новый заказ появляется у оператора | D66: Выполнен OFR-01 | E66: 1. [Оператор] Обновить /orders?branch_id=79. | F66: Заказ в списке: номер, клиент (имя, телефон), мерчант Pepsi Market, Итого, оплата, статус «Подтверждён», дата = время оформления. | G66: P0 | H66: + | I66: Smoke | J66: Безопасно | L66: 29.09: «Дата» 16:32 = создание корзины, оформление 16:34 — BUG-D07
A67: OPR-02 | B67: Оператор | C67: Карточка заказа совпадает с клиентом | D67: Заказ создан; открыта его карточка | E67: 1. [Оператор] Сверить товары, кол-во, цены, доставку, Итого, оплату, адрес, телефон с экраном клиента. | F67: Все данные совпадают; адрес доставки заполнен. | G67: P0 | H67: + | I67: Smoke | J67: Безопасно | L67: 29.09: адрес «—» (TEZ00871, TEZ00798) — BUG-D06
A68: OPR-03 | B68: Оператор | C68: История статусов | D68: Заказ прошёл весь основной путь | E68: 1. [Оператор] Открыть историю статусов. | F68: Каждый переход записан один раз, по порядку, со временем и автором (мерчант / курьер / система / клиент). | G68: P1 | H68: + | I68: Sanity | J68: Безопасно | L68: 29.09: у перехода «Готов к доставке → В пути» автор не указан
A69: OPR-04 | B69: Оператор | C69: Фильтры статусов | D69: Выполняется на каждом этапе основного пути | E69: 1. [Оператор] Выбрать фильтр текущего статуса. 2. Выбрать фильтр предыдущего статуса. | F69: Заказ находится только в фильтре текущего статуса. | G69: P1 | H69: + | I69: Sanity | J69: Безопасно
A70: OPR-05 | B70: Оператор | C70: Курьер виден в заказе | D70: Заказ Pepsi Market (наличные); клиент на экране 03 | E70: 1. [Оператор] Проверить список и карточку. | F70: Таксопарк/курьер указаны в списке и в карточке; имя = имени на клиенте. | G70: P1 | H70: + | I70: Sanity | J70: Безопасно | L70: 29.09: курьер только в списке — BUG-D08
A71: OPR-06 | B71: Оператор | C71: Проблемные заказы заметны оператору | D71: Выполняется в RPL-01, DLY-01, DLY-03, DLY-05, UNV-01, UNV-04 | E71: 1. [Оператор] На каждом проблемном состоянии осмотреть список, карточку, колокольчик уведомлений. | F71: Оператор видит проблему (метка, подсветка, уведомление или фильтр). Записать, где и как. | G71: P1 | H71: + | I71: Sanity | J71: Безопасно | L71: Q-D02: в панели нет статусов и фильтров для проблем
A72: OPR-07 | B72: Оператор | C72: Уведомления оператора | D72: Открыта панель оператора | E72: 1. Создать новый заказ. 2. Вызвать проблемное состояние. 3. Проверить колокольчик. | F72: Уведомления о новом заказе и о проблемах (если предусмотрены); переход из уведомления открывает заказ. | G72: P2 | H72: + | I72: Regression | J72: Безопасно
A73: OPR-08 | B73: Оператор | C73: Ручная смена статуса оператором | D73: Заказ Pepsi Market (наличные); клиент на экране 02; только тестовый заказ | E73: 1. [Оператор] «Изменить статус» → следующий статус → комментарий → «Сохранить». 2. [Клиент] Смотреть на экран. | F73: Статус изменён; в истории автор — оператор, комментарий сохранён; клиент получил новый экран. | G73: P2 | H73: + | I73: Regression | J73: Меняет данные | L73: Только на своём тестовом заказе
A74: OPR-09 | B74: Оператор | C74: Доступ роли «Оператор» | D74: Выйти из панели | E74: 1. Войти под ролью оператора. 2. Посмотреть меню. 3. Открыть /store напрямую. | F74: После входа открывается «Заказы»; в меню только доступные разделы; прямой URL недоступного раздела — 403. | G74: P2 | H74: − | I74: Regression | J74: Безопасно | L74: 29.09: после входа 403 на /dashboard; в меню видны недоступные разделы — BUG-D10, BUG-D11
A75: OPR-10 | B75: Оператор | C75: Контакты поддержки в панели | D75: Открыта панель | E75: 1. Навести курсор на «Телефон» и «Telegram службы поддержки», посмотреть адреса ссылок (не переходить). | F75: Ссылки ведут на официальные контакты сервиса. | G75: P1 | H75: − | I75: Sanity | J75: Безопасно | L75: 29.09: Telegram → fl4y…oastify.com — BUG-D09
A76: OPR-11 | B76: Оператор | C76: Поиск заказа | D76: Есть тестовый заказ | E76: 1. [Оператор] Найти заказ по номеру. 2. Найти по телефону клиента. | F76: Заказ находится в обоих случаях. | G76: P2 | H76: + | I76: Regression | J76: Безопасно
A77: CUR-01 | B77: Курьер | C77: Заказ в ленте курьера | D77: Заказ «Готов к доставке» | E77: 1. [Курьер] Открыть ленту, открыть заказ. | F77: Магазин, адрес клиента, состав, способ оплаты, сумма к получению (для наличных) = Итог клиента. | G77: P0 | H77: + | I77: Smoke | J77: Реальный заказ
A78: CUR-02 | B78: Курьер | C78: Действия курьера по этапам | D78: Заказ принят курьером | E78: 1. [Курьер] На каждом этапе проверить доступные кнопки. | F78: Доступно только следующее действие: принять → забрал → на месте → передал; этапы не пропускаются. | G78: P1 | H78: ± | I78: Sanity | J78: Реальный заказ
A79: CUR-03 | B79: Курьер | C79: Таймер ожидания у курьера | D79: Заказ Pepsi Market (наличные); клиент на экране 05 | E79: 1. Сравнить таймер у курьера и у клиента. | F79: Расхождение не больше 5 с. | G79: P2 | H79: + | I79: Regression | J79: Реальный заказ
A80: CUR-04 | B80: Курьер | C80: Кнопка «Клиент не отвечает» | D80: Заказ Pepsi Market (наличные); клиент на экране 05 | E80: 1. [Курьер] Найти действие для недоступного клиента. | F80: Действие есть (или в таймаут переход автоматический — записать, как устроено); клиент получает 05A. | G80: P1 | H80: + | I80: Sanity | J80: Реальный заказ
A81: CUR-05 | B81: Курьер | C81: Инструкции курьеру при недоставке | D81: Выполнен UNV-04 | E81: 1. [Курьер] Открыть заказ. | F81: Понятно, что делать с заказом (вернуть в магазин и т. п.); заказ не висит в активных. | G81: P2 | H81: + | I81: Regression | J81: Реальный заказ

Sheet Прогон
A1: Прогон флоу доставки (шаблон) — скопируйте лист на каждую сборку
A3: Сборка (версия) | B3: 1.1.8 (43) | E3: Всего кейсов | F3: =COUNTA($A$12:$A$91) -> 80 | H3: Smoke выполнено | I3: =COUNTIFS($E$12:$E$91,"Smoke",$G$12:$G$91,"<>")&" из "&COUNTIF($E$12:$E$91,"Smoke") -> 0 из 11
A4: Дата | E4: Pass | F4: =COUNTIF($G$12:$G$91,"Pass") -> 0 | H4: Smoke Fail | I4: =COUNTIFS($E$12:$E$91,"Smoke",$G$12:$G$91,"Fail") -> 0
A5: Тестировщик | E5: Fail | F5: =COUNTIF($G$12:$G$91,"Fail") -> 0 | H5: P0 Fail | I5: =COUNTIFS($D$12:$D$91,"P0",$G$12:$G$91,"Fail") -> 0
A6: Устройство клиента | E6: Blocked | F6: =COUNTIF($G$12:$G$91,"Blocked") -> 0 | H6: Вердикт | I6: =IF(I4>0,"НЕ ГОДЕН: упал Smoke",IF(I5>0,"НЕ ГОДЕН: упал P0",IF(COUNTIFS($E$12:$E$91,"Smoke",$G$12:$G$91,"")>0,"Smoke не завершён","Smoke пройден"))) -> Smoke не завершён
A7: Вид прогона | E7: Skip | F7: =COUNTIF($G$12:$G$91,"Skip") -> 0
A8: Номера заказов | E8: Не выполнено | F8: =F3-F4-F5-F6-F7 -> 80
E9: % Pass (из выполненных) | F9: =IF(F4+F5+F6=0,"-",F4/(F4+F5+F6)) -> -
A10: Жёлтые ячейки — заполнять. Пример строки: DLV-03 | Fail | BUG-D08 | «TEZ00871: в панели сразу «В пути», курьера в карточке нет».
A11: ID | B11: Модуль | C11: Название | D11: Приоритет | E11: Набор | F11: Риск | G11: Статус | H11: Баг | I11: Комментарий (№ заказа, факт)
A12: OFR-01 | B12: =IFERROR(INDEX('Тест-кейсы'!$B$2:$B$81,MATCH($A12,'Тест-кейсы'!$A$2:$A$81,0)),"") -> Оформление | C12: =IFERROR(INDEX('Тест-кейсы'!$C$2:$C$81,MATCH($A12,'Тест-кейсы'!$A$2:$A$81,0)),"") -> Оформление заказа с доставкой, наличные | D12: =IFERROR(INDEX('Тест-кейсы'!$G$2:$G$81,MATCH($A12,'Тест-кейсы'!$A$2:$A$81,0)),"") -> P0 | E12: =IFERROR(INDEX('Тест-кейсы'!$I$2:$I$81,MATCH($A12,'Тест-кейсы'!$A$2:$A$81,0)),"") -> Smoke | F12: =IFERROR(INDEX('Тест-кейсы'!$J$2:$J$81,MATCH($A12,'Тест-кейсы'!$A$2:$A$81,0)),"") -> Реальный заказ
A13: OFR-02 | B13: =IFERROR(INDEX('Тест-кейсы'!$B$2:$B$81,MATCH($A13,'Тест-кейсы'!$A$2:$A$81,0)),"") -> Оформление | C13: =IFERROR(INDEX('Тест-кейсы'!$C$2:$C$81,MATCH($A13,'Тест-кейсы'!$A$2:$A$81,0)),"") -> Экран успеха после оформления | D13: =IFERROR(INDEX('Тест-кейсы'!$G$2:$G$81,MATCH($A13,'Тест-кейсы'!$A$2:$A$81,0)),"") -> P1 | E13: =IFERROR(INDEX('Тест-кейсы'!$I$2:$I$81,MATCH($A13,'Тест-кейсы'!$A$2:$A$81,0)),"") -> Sanity | F13: =IFERROR(INDEX('Тест-кейсы'!$J$2:$J$81,MATCH($A13,'Тест-кейсы'!$A$2:$A$81,0)),"") -> Реальный заказ
A14: OFR-03 | B14: =IFERROR(INDEX('Тест-кейсы'!$B$2:$B$81,MATCH($A14,'Тест-кейсы'!$A$2:$A$81,0)),"") -> Оформление | C14: =IFERROR(INDEX('Тест-кейсы'!$C$2:$C$81,MATCH($A14,'Тест-кейсы'!$A$2:$A$81,0)),"") -> Оформление заказа картой | D14: =IFERROR(INDEX('Тест-кейсы'!$G$2:$G$81,MATCH($A14,'Тест-кейсы'!$A$2:$A$81,0)),"") -> P1 | E14: =IFERROR(INDEX('Тест-кейсы'!$I$2:$I$81,MATCH($A14,'Тест-кейсы'!$A$2:$A$81,0)),"") -> Sanity | F14: =IFERROR(INDEX('Тест-кейсы'!$J$2:$J$81,MATCH($A14,'Тест-кейсы'!$A$2:$A$81,0)),"") -> Реальный заказ
A15: TRK-01 | B15: =IFERROR(INDEX('Тест-кейсы'!$B$2:$B$81,MATCH($A15,'Тест-кейсы'!$A$2:$A$81,0)),"") -> Отслеживание | C15: =IFERROR(INDEX('Тест-кейсы'!$C$2:$C$81,MATCH($A15,'Тест-кейсы'!$A$2:$A$81,0)),"") -> Экран 01 «Ждём подтверждения магазина» | D15: =IFERROR(INDEX('Тест-кейсы'!$G$2:$G$81,MATCH($A15,'Тест-кейсы'!$A$2:$A$81,0)),"") -> P0 | E15: =IFERROR(INDEX('Тест-кейсы'!$I$2:$I$81,MATCH($A15,'Тест-кейсы'!$A$2:$A$81,0)),"") -> Smoke | F15: =IFERROR(INDEX('Тест-кейсы'!$J$2:$J$81,MATCH($A15,'Тест-кейсы'!$A$2:$A$81,0)),"") -> Реальный заказ
A16: TRK-02 | B16: =IFERROR(INDEX('Тест-кейсы'!$B$2:$B$81,MATCH($A16,'Тест-кейсы'!$A$2:$A$81,0)),"") -> Отслеживание | C16: =IFERROR(INDEX('Тест-кейсы'!$C$2:$C$81,MATCH($A16,'Тест-кейсы'!$A$2:$A$81,0)),"") -> «Посмотреть» — состав заказа | D16: =IFERROR(INDEX('Тест-кейсы'!$G$2:$G$81,MATCH($A16,'Тест-кейсы'!$A$2:$A$81,0)),"") -> P1 | E16: =IFERROR(INDEX('Тест-кейсы'!$I$2:$I$81,MATCH($A16,'Тест-кейсы'!$A$2:$A$81,0)),"") -> Sanity | F16: =IFERROR(INDEX('Тест-кейсы'!$J$2:$J$81,MATCH($A16,'Тест-кейсы'!$A$2:$A$81,0)),"") -> Реальный заказ
A17: TRK-03 | B17: =IFERROR(INDEX('Тест-кейсы'!$B$2:$B$81,MATCH($A17,'Тест-кейсы'!$A$2:$A$81,0)),"") -> Отслеживание | C17: =IFERROR(INDEX('Тест-кейсы'!$C$2:$C$81,MATCH($A17,'Тест-кейсы'!$A$2:$A$81,0)),"") -> Кнопка «Помощь» | D17: =IFERROR(INDEX('Тест-кейсы'!$G$2:$G$81,MATCH($A17,'Тест-кейсы'!$A$2:$A$81,0)),"") -> P1 | E17: =IFERROR(INDEX('Тест-кейсы'!$I$2:$I$81,MATCH($A17,'Тест-кейсы'!$A$2:$A$81,0)),"") -> Sanity | F17: =IFERROR(INDEX('Тест-кейсы'!$J$2:$J$81,MATCH($A17,'Тест-кейсы'!$A$2:$A$81,0)),"") -> Реальный заказ
A18: TRK-04 | B18: =IFERROR(INDEX('Тест-кейсы'!$B$2:$B$81,MATCH($A18,'Тест-кейсы'!$A$2:$A$81,0)),"") -> Отслеживание | C18: =IFERROR(INDEX('Тест-кейсы'!$C$2:$C$81,MATCH($A18,'Тест-кейсы'!$A$2:$A$81,0)),"") -> Шеврон «свернуть» и возврат к заказу | D18: =IFERROR(INDEX('Тест-кейсы'!$G$2:$G$81,MATCH($A18,'Тест-кейсы'!$A$2:$A$81,0)),"") -> P2 | E18: =IFERROR(INDEX('Тест-кейсы'!$I$2:$I$81,MATCH($A18,'Тест-кейсы'!$A$2:$A$81,0)),"") -> Regression | F18: =IFERROR(INDEX('Тест-кейсы'!$J$2:$J$81,MATCH($A18,'Тест-кейсы'!$A$2:$A$81,0)),"") -> Реальный заказ
A19: TRK-05 | B19: =IFERROR(INDEX('Тест-кейсы'!$B$2:$B$81,MATCH($A19,'Тест-кейсы'!$A$2:$A$81,0)),"") -> Отслеживание | C19: =IFERROR(INDEX('Тест-кейсы'!$C$2:$C$81,MATCH($A19,'Тест-кейсы'!$A$2:$A$81,0)),"") -> Блок «Общая стоимость» | D19: =IFERROR(INDEX('Тест-кейсы'!$G$2:$G$81,MATCH($A19,'Тест-кейсы'!$A$2:$A$81,0)),"") -> P0 | E19: =IFERROR(INDEX('Тест-кейсы'!$I$2:$I$81,MATCH($A19,'Тест-кейсы'!$A$2:$A$81,0)),"") -> Smoke | F19: =IFERROR(INDEX('Тест-кейсы'!$J$2:$J$81,MATCH($A19,'Тест-кейсы'!$A$2:$A$81,0)),"") -> Реальный заказ
A20: TRK-06 | B20: =IFERROR(INDEX('Тест-кейсы'!$B$2:$B$81,MATCH($A20,'Тест-кейсы'!$A$2:$A$81,0)),"") -> Отслеживание | C20: =IFERROR(INDEX('Тест-кейсы'!$C$2:$C$81,MATCH($A20,'Тест-кейсы'!$A$2:$A$81,0)),"") -> Подсказка «Итог может измениться…» по этапам | D20: =IFERROR(INDEX('Тест-кейсы'!$G$2:$G$81,MATCH($A20,'Тест-кейсы'!$A$2:$A$81,0)),"") -> P2 | E20: =IFERROR(INDEX('Тест-кейсы'!$I$2:$I$81,MATCH($A20,'Тест-кейсы'!$A$2:$A$81,0)),"") -> Regression | F20: =IFERROR(INDEX('Тест-кейсы'!$J$2:$J$81,MATCH($A20,'Тест-кейсы'!$A$2:$A$81,0)),"") -> Реальный заказ
A21: TRK-07 | B21: =IFERROR(INDEX('Тест-кейсы'!$B$2:$B$81,MATCH($A21,'Тест-кейсы'!$A$2:$A$81,0)),"") -> Отслеживание | C21: =IFERROR(INDEX('Тест-кейсы'!$C$2:$C$81,MATCH($A21,'Тест-кейсы'!$A$2:$A$81,0)),"") -> Степпер соответствует этапу | D21: =IFERROR(INDEX('Тест-кейсы'!$G$2:$G$81,MATCH($A21,'Тест-кейсы'!$A$2:$A$81,0)),"") -> P1 | E21: =IFERROR(INDEX('Тест-кейсы'!$I$2:$I$81,MATCH($A21,'Тест-кейсы'!$A$2:$A$81,0)),"") -> Sanity | F21: =IFERROR(INDEX('Тест-кейсы'!$J$2:$J$81,MATCH($A21,'Тест-кейсы'!$A$2:$A$81,0)),"") -> Реальный заказ
A22: TRK-08 | B22: =IFERROR(INDEX('Тест-кейсы'!$B$2:$B$81,MATCH($A22,'Тест-кейсы'!$A$2:$A$81,0)),"") -> Отслеживание | C22: =IFERROR(INDEX('Тест-кейсы'!$C$2:$C$81,MATCH($A22,'Тест-кейсы'!$A$2:$A$81,0)),"") -> Открытие активного заказа из «Заказов» | D22: =IFERROR(INDEX('Тест-кейсы'!$G$2:$G$81,MATCH($A22,'Тест-кейсы'!$A$2:$A$81,0)),"") -> P1 | E22: =IFERROR(INDEX('Тест-кейсы'!$I$2:$I$81,MATCH($A22,'Тест-кейсы'!$A$2:$A$81,0)),"") -> Sanity | F22: =IFERROR(INDEX('Тест-кейсы'!$J$2:$J$81,MATCH($A22,'Тест-кейсы'!$A$2:$A$81,0)),"") -> Реальный заказ
A23: TRK-09 | B23: =IFERROR(INDEX('Тест-кейсы'!$B$2:$B$81,MATCH($A23,'Тест-кейсы'!$A$2:$A$81,0)),"") -> Отслеживание | C23: =IFERROR(INDEX('Тест-кейсы'!$C$2:$C$81,MATCH($A23,'Тест-кейсы'!$A$2:$A$81,0)),"") -> Формат времени доставки | D23: =IFERROR(INDEX('Тест-кейсы'!$G$2:$G$81,MATCH($A23,'Тест-кейсы'!$A$2:$A$81,0)),"") -> P2 | E23: =IFERROR(INDEX('Тест-кейсы'!$I$2:$I$81,MATCH($A23,'Тест-кейсы'!$A$2:$A$81,0)),"") -> Regression | F23: =IFERROR(INDEX('Тест-кейсы'!$J$2:$J$81,MATCH($A23,'Тест-кейсы'!$A$2:$A$81,0)),"") -> Реальный заказ
... A91: CUR-05 | B91: =IFERROR(INDEX('Тест-кейсы'!$B$2:$B$81,MATCH($A91,'Тест-кейсы'!$A$2:$A$81,0)),"") -> Курьер | C91: =IFERROR(INDEX('Тест-кейсы'!$C$2:$C$81,MATCH($A91,'Тест-кейсы'!$A$2:$A$81,0)),"") -> Инструкции курьеру при недоставке | D91: =IFERROR(INDEX('Тест-кейсы'!$G$2:$G$81,MATCH($A91,'Тест-кейсы'!$A$2:$A$81,0)),"") -> P2 | E91: =IFERROR(INDEX('Тест-кейсы'!$I$2:$I$81,MATCH($A91,'Тест-кейсы'!$A$2:$A$81,0)),"") -> Regression | F91: =IFERROR(INDEX('Тест-кейсы'!$J$2:$J$81,MATCH($A91,'Тест-кейсы'!$A$2:$A$81,0)),"") -> Реальный заказ

Sheet Баги
A1: ID | B1: Модуль | C1: Заголовок | D1: Шаги | E1: Факт | F1: Ожидание | G1: Серьёзность | H1: Статус | I1: Найден в | J1: Кейс | K1: Дата | L1: Комментарий / трекер
A2: BUG-D01 | B2: Оформление | C2: Итог заказа не включает стоимость доставки | D2: 1. Pepsi Market, 1 товар 2 000. 2. Оформить с доставкой. 3. Посмотреть блок стоимости в отслеживании и в панели. | E2: Доставка 12 000, Итог 2 000 — и у клиента, и в панели («Итого» 2 000). | F2: Итог = товары + доставка (14 000) или явное пояснение, что доставка оплачивается отдельно. | G2: Critical | H2: Перепроверить | I2: 1.1.8 (43), TEZ00871 | J2: TRK-05 | K2: 2026-09-29 | L2: Возможно, дубль бага из основного тест-плана («Jami не включает доставку»). См. Q-D04
A3: BUG-D02 | B3: Оформление | C3: На экране оформления не показана стоимость доставки | D3: 1. Pepsi Market, 1 товар. 2. Открыть оформление, посмотреть блок стоимости. | E3: Строки доставки нет. | F3: Стоимость доставки показана до оформления. | G3: Major | H3: Перепроверить | I3: 1.1.8 (43), TEZ00871 | J3: OFR-01 | K3: 2026-09-29
A4: BUG-D03 | B4: Оформление | C4: Экран успеха: «Стоимость доставки 0 сум» | D4: 1. Оформить заказ с доставкой 12 000. 2. Посмотреть экран успеха. | E4: «Стоимость доставки 0 сум». | F4: Сумма доставки = 12 000, как в панели. | G4: Major | H4: Перепроверить | I4: 1.1.8 (43), TEZ00871 | J4: OFR-02 | K4: 2026-09-29
A5: BUG-D04 | B5: Оформление | C5: Экран успеха: подпись «Способ пополнения» вместо «Способ оплаты» | D5: 1. Оформить заказ. 2. Посмотреть экран успеха. | E5: «Способ пополнения». | F5: «Способ оплаты». | G5: Minor | H5: Перепроверить | I5: 1.1.8 (43), TEZ00871 | J5: OFR-02 | K5: 2026-09-29
A6: BUG-D05 | B6: Оформление | C6: Экран успеха: время в 12-часовом формате без AM/PM | D6: 1. Оформить заказ в 16:34. 2. Посмотреть время на экране успеха. | E6: 04:34. | F6: 16:34. | G6: Minor | H6: Перепроверить | I6: 1.1.8 (43), TEZ00871 | J6: OFR-02 | K6: 2026-09-29
A7: BUG-D06 | B7: Оператор | C7: Карточка заказа: адрес доставки «—» | D7: 1. Оформить заказ с доставкой на сохранённый адрес. 2. Оператор: открыть карточку заказа. | E7: «Адрес: —». | F7: Адрес доставки клиента. | G7: Major | H7: Новый | I7: панель, TEZ00871, TEZ00798 | J7: OPR-02 | K7: 2026-09-29 | L7: Воспроизвелось на двух заказах
A8: BUG-D07 | B8: Оператор | C8: «Дата» заказа = время создания корзины, а не оформления | D8: 1. Оформить заказ. 2. Сравнить «Дату» в списке/карточке с историей и с экраном клиента. | E8: Дата 16:32, в истории «Корзина → Подтверждён» 16:34, клиент оформил в 16:34. | F8: Дата = время оформления. | G8: Minor | H8: Перепроверить | I8: панель, TEZ00871 | J8: OPR-01 | K8: 2026-09-29
A9: BUG-D08 | B9: Оператор | C9: Нет этапа «Назначен курьер»: после «Готов к доставке» сразу «В пути» | D9: 1. Мерчант: «Готов к доставке». 2. Курьер: принять заказ. 3. Оператор: история и статус. | E9: 16:39 «Готов к доставке» → 16:39 «В пути» (без автора); «Назначен курьер» / «Передан курьеру» нет; в карточке нет курьера. | F9: Отдельные статусы принятия и получения заказа курьером; курьер в карточке. | G9: Major | H9: Перепроверить | I9: панель, TEZ00871 | J9: DLV-03 | K9: 2026-09-29 | L9: Уточнить, нажимал ли курьер «Забрал» сразу после принятия
A10: BUG-D09 | B10: Оператор | C10: Ссылка «Telegram службы поддержки» ведёт на oastify.com | D10: 1. Открыть панель. 2. Посмотреть адрес ссылки «Telegram» в блоке поддержки (не переходить). | E10: https://fl4yjwfo617p0uoubrh8dhu1nstjhb50.oastify.com/offHands (домен Burp Collaborator). | F10: Официальный Telegram службы поддержки. | G10: Critical | H10: Новый | I10: панель, 29.09 | J10: OPR-10 | K10: 2026-09-29 | L10: Безопасность: похоже на оставленный тестовый или подменённый URL. Передать разработчикам, по ссылке не переходить
A11: BUG-D10 | B11: Оператор | C11: После входа оператора — 403 на /dashboard | D11: 1. Войти под ролью оператора (ссылка входа с redirect=/dashboard). | E11: Страница «403 Нет доступа». | F11: Сразу раздел «Заказы». | G11: Minor | H11: Новый | I11: панель, 29.09 | J11: OPR-09 | K11: 2026-09-29
A12: BUG-D11 | B12: Оператор | C12: В меню оператора видны недоступные разделы | D12: 1. Войти под ролью оператора. 2. Посмотреть боковое меню. | E12: Видны «Мой магазин», «Магазины», «POS», «Таксопарки», «Курьеры», «Пользователи»; доступны только «Заказы». | F12: Показаны только доступные роли разделы. | G12: Trivial | H12: Новый | I12: панель, 29.09 | J12: OPR-09 | K12: 2026-09-29
A13: BUG-D12 | B13: Оператор | C13: «Всего: 1 заказов» — неверное склонение | D13: 1. Отфильтровать список так, чтобы остался 1 заказ. | E13: «Всего: 1 заказов». | F13: «Всего: 1 заказ». | G13: Trivial | H13: Новый | I13: панель, 29.09 | J13: OPR-04 | K13: 2026-09-29

Sheet Вопросы
A1: ID | B1: Вопрос | C1: Связано с | D1: Ответ | E1: Дата ответа
A2: Q-D01 | B2: В панели нет статуса «Ожидает»: заказ сразу «Подтверждён» (история «Корзина → Подтверждён»). Какой статус означает «ждём подтверждения магазина» (экран 01), а какой — «магазин принял»? | C2: TRK-01, DLV-01, OPR-01
A3: Q-D02 | B3: В панели нет статуса «Курьер на месте» и признаков проблем (замена, задержки, клиент недоступен). Как оператор должен узнавать о них? | C3: DLV-06, OPR-06
A4: Q-D03 | B4: На экране 01 в сборке есть отмена клиентом, в макете её нет. Что правильно? | C4: CNL-01…CNL-04
A5: Q-D04 | B5: Итог не включает доставку (2 000 при доставке 12 000). Так задумано (доставка оплачивается курьеру отдельно) или это баг? | C5: BUG-D01, TRK-05
A6: Q-D05 | B6: Значения таймеров: автоотмена без подтверждения, таймер замены, пороги задержки сборки / поиска курьера / доставки, ожидание у двери, таймаут «клиент недоступен → не доставлен». | C6: REJ-04, RPL-07, DLY-*, UNV-*
A7: Q-D06 | B7: Что видит клиент при отклонении заказа, оплаченного наличными (01A без блока возврата)? | C7: REJ-02
A8: Q-D07 | B8: Что видит клиент после отмены мерчантом уже собираемого заказа и после решения по недоставке? | C8: REJ-05, UNV-06
A9: Q-D08 | B9: Подсказка «Итог может измениться…» на 03 и 02A, где заказ уже собран, — нужна ли? С какого статуса сумма окончательная? | C9: TRK-06
A10: Q-D09 | B10: Как клиенту показывается автоудаление товаров по таймеру замены? Что происходит, если закончились все товары? | C10: RPL-07, RPL-09
A11: Q-D10 | B11: 02A: текст «Заказ уже собран», а степпер на шаге сборки. Что показывать, если курьера долго ищут, пока сборка ещё идёт? | C11: DLY-03
A12: Q-D11 | B12: Нужен ли на 05A таймер ожидания (на 05 он есть)? | C12: UNV-01
A13: Q-D12 | B13: Какой экран открывает «Выбрать» на 02B? В макете его нет. | C13: RPL-04
... A15: Q-D14 | B15: Какой статус панели соответствует недоставке (05B): «Возвращён» или другой? | C15: UNV-04
